rustic/__init__.py
rustic/__main__.py
tests/__init__.py
rustic-0.0.1.dist-info/LICENSE
rustic-0.0.1.dist-info/METADATA
rustic-0.0.1.dist-info/WHEEL
rustic-0.0.1.dist-info/entry_points.txt
rustic-0.0.1.dist-info/top_level.txt
rustic-0.0.1.dist-info/RECORD
